<annotation>
	<folder>images</folder>
	<filename>00016.jpg</filename>
	<path>C:\Code\Python\Mask_RCNN\weed\images\00016.jpg</path>
	<source>
		<database>Unknown</database>
	</source>
	<size>
		<width>4032</width>
		<height>3024</height>
		<depth>3</depth>
	</size>
	<segmented>0</segmented>
    <object>
		<name>Weed</name>
		<pose>Unspecified</pose>
		<truncated>0</truncated>
		<difficult>0</difficult>
		<bndbox>
			<xmin>41</xmin>
			<ymin>1517</ymin>
			<xmax>969</xmax>
			<ymax>2345</ymax>
		</bndbox>
	</object>
    <object>
		<name>Weed</name>
		<pose>Unspecified</pose>
		<truncated>0</truncated>
		<difficult>0</difficult>
		<bndbox>
			<xmin>605</xmin>
			<ymin>941</ymin>
			<xmax>1509</xmax>
			<ymax>1909</ymax>
		</bndbox>
	</object>
    <object>
		<name>Weed</name>
		<pose>Unspecified</pose>
		<truncated>0</truncated>
		<difficult>0</difficult>
		<bndbox>
			<xmin>1369</xmin>
			<ymin>1077</ymin>
			<xmax>1957</xmax>
			<ymax>1801</ymax>
		</bndbox>
	</object>
</annotation>